{
  "condition": {
    "plugin": {
      "list": []
    },
    "game": {
      "list": []
    },
    "gamePlugin": {
      "list": []
    },
    "miniprogram": {
      "list": [
        {
          "name": "pages/index/index",
          "pathName": "pages/index/index",
          "query": "",
          "scene": null
        },
        {
          "name": "分类页面",
          "pathName": "pages/category/index",
          "query": "",
          "scene": null
        },
        {
          "name": "商品列表",
          "pathName": "pages/goods_list/index",
          "query": "cat_id=5",
          "scene": null
        },
        {
          "name": "商品详情",
          "pathName": "pages/goods_detail/index",
          "query": "goods_id=57444",
          "scene": null
        },
        {
          "name": "结合ssm",
          "pathName": "pages/demo2/demo2",
          "query": "goods_id=57444",
          "scene": null
        },
        {
          "name": "我的",
          "pathName": "pages/user/index",
          "query": "",
          "scene": null
        },
        {
          "name": "添加商品",
          "pathName": "pages/addGoods/index",
          "query": "",
          "scene": null
        },
        {
          "name": "商品详情",
          "pathName": "pages/goods_detail/index",
          "query": "goods_name=百草味大面筋",
          "scene": null
        },
        {
          "name": "搜索",
          "pathName": "pages/search/index",
          "scene": null
        }
      ]
    }
  }
}